fastinference/__init__.py
fastinference/_nbdev.py
fastinference/class_confusion.py
fastinference/onnx.py
fastinference/soft_dependencies.py
fastinference/inference/__init__.py
fastinference/inference/export.py
fastinference/inference/inference.py
fastinference/inference/text.py
fastinference/tabular/__init__.py
fastinference/tabular/core.py
fastinference/tabular/interpretation.py
fastinference/tabular/pd.py
fastinference/tabular/waterfall.py
fastinference/tabular/shap/__init__.py
fastinference/tabular/shap/core.py
fastinference/tabular/shap/interp.py
fastinference-0.0.36.dist-info/METADATA
fastinference-0.0.36.dist-info/RECORD
fastinference-0.0.36.dist-info/WHEEL
fastinference-0.0.36.dist-info/entry_points.txt
fastinference-0.0.36.dist-info/top_level.txt
